lineup_lang/VERSION
lineup_lang/__init__.py
lineup_lang/args_resolver.py
lineup_lang/error.py
lineup_lang/language_object.py
lineup_lang/line_decoder.py
lineup_lang/logger.py
lineup_lang/core/__init__.py
lineup_lang/core/conditions.py
lineup_lang/core/system.py
lineup_lang/core/variables.py
lineup_lang/executor/__init__.py
lineup_lang/executor/default.py
lineup_lang/executor/jump.py
lineup_lang-0.2.0.dist-info/licenses/LICENSE
lineup_lang-0.2.0.dist-info/METADATA
lineup_lang-0.2.0.dist-info/WHEEL
lineup_lang-0.2.0.dist-info/top_level.txt
lineup_lang-0.2.0.dist-info/RECORD
