Metadata-Version: 2.4
Name: lineup-lang
Version: 0.2.0
Summary: Pseudo language interpreter for Python
Home-page: https://github.com/alex-bouget/Lineup
Author: alex-bouget
Classifier: Development Status :: 4 - Beta
Classifier: Environment :: Console
Classifier: Intended Audience :: Developers
Classifier: License :: OSI Approved :: GNU General Public License v3 (GPLv3)
Classifier: Programming Language :: Python :: 3 :: Only
Classifier: Topic :: Software Development :: Interpreters
License-File: LICENSE
Requires-Dist: regex
Dynamic: author
Dynamic: classifier
Dynamic: description
Dynamic: description-content-type
Dynamic: home-page
Dynamic: license-file
Dynamic: requires-dist
Dynamic: summary
